[{"timestamp":1713464140105,"id":2157,"title":"Exclusive: President's Surprising Twist in Supreme Court Showdown Could Upend Impeachment and Tax Laws Forever","keywords":["President","Supreme Court","political satire","impeachment","taxation"],"address":"2157-exclusive-presidents-surprising-twist-in-supreme-court-showdown-could-upend.html"},{"timestamp":1713464111274,"id":2156,"title":"Revealed: How the Next President's Tax Plan Could Redefine American Democracy in a Starkly Dystopian Sh","keywords":["Constitution","taxation","dystopian","campaign","President"],"address":"2156-revealed-how-the-next-presidents-tax-plan-could-redefine-american.html"},{"timestamp":1713464083504,"id":2155,"title":"Exclusive: The President's Shocking New Proposal to Tax Virtual Winnings Amidst a National Gaming Boom as Economic","keywords":["President","taxation","gaming","legislation","disaster"],"address":"2155-exclusive-the-presidents-shocking-new-proposal-to-tax-virtual-winnings.html"},{"timestamp":1713464058426,"id":2154,"title":"Exclusive: How Political Satire Unmasked the Economic Mastermind Behind the Latest Global Conflict Backed by a Surprise Alliance of","keywords":["political satire","Democrats","political games","war","economics"],"address":"2154-exclusive-how-political-satire-unmasked-the-economic-mastermind-behind-the.html"},{"timestamp":1713464031893,"id":2153,"title":"Exclusive Report: How a Gaming Strategy Uncovered a Web of Corruption in Tax Policies Proposed by Republicans","keywords":["taxation","Republicans","gaming","strategy games","corruption"],"address":"2153-exclusive-report-how-a-gaming-strategy-uncovered-a-web-of.html"},{"timestamp":1713464002207,"id":2152,"title":"Unveiling the Shadows: How Historical Tactics and Political Satire Have Shaped the Downfall of Corrupt Leaders - Less","keywords":["history","political strategy","political satire","corruption","impeached"],"address":"2152-unveiling-the-shadows-how-historical-tactics-and-political-satire-have.html"},{"timestamp":1713463971626,"id":2151,"title":"Exclusive Report: How a Radical New Tax Strategy Could Reshape Political Power in the House and Ignite a National Debate on","keywords":["taxation","political strategy","House of Representatives","political satire","freedom"],"address":"2151-exclusive-report-how-a-radical-new-tax-strategy-could-reshape.html"}]