[{"timestamp":1699930390157,"id":12,"title":"Supreme Court Rules Impeachment Must Consider Economic Impact on Future Generations","keywords":["Supreme Court","economics","impeached","futurism"]},{"timestamp":1699930359735,"id":11,"title":"Congress Probes New Senate Political Strategy in Wake of Supreme Court Ruling","keywords":["Congress","political strategy","Senate","Supreme Court"]},{"timestamp":1699930338555,"id":10,"title":"Freedom's Fury: Satirical Candidate Storms Political Stage with Unconventional Strategy","keywords":["freedom","political satire","politics","political strategy"]},{"timestamp":1699930316002,"id":9,"title":"Constitutional Clash: Mobile Games Fuel War over Government Power","keywords":["Constitution","Government","mobile games","war"]},{"timestamp":1699930296814,"id":8,"title":"Supreme Court Rules in Favor of Gaming Industry in Landmark Dystopian Future Case","keywords":["gaming","Supreme Court","dystopian","House of Representatives"]},{"timestamp":1699930274263,"id":7,"title":"Scientists Discover New Economic Paradigm Shift: The End of Capitalism as We Know It?","keywords":["economics","science","history","politics"]},{"timestamp":1699930246412,"id":6,"title":"Democrats Play Dystopian Political Games to Maintain Freedom","keywords":["dystopian","political games","freedom","Democrats"]},{"timestamp":1699930224586,"id":5,"title":"House of Representatives Corruption Reaches New Dystopian Heights","keywords":["politics","dystopian","corruption","House of Representatives"]},{"timestamp":1699930195748,"id":4,"title":"House of Representatives Votes to Impeach Corrupt Government Official","keywords":["Government","corruption","impeachment","House of Representatives"]},{"timestamp":1699930171929,"id":3,"title":"Scientific Impeachment Strategy: A New Approach to Enforce Constitutional Rights","keywords":["Constitution","science","political strategy","impeachment"]},{"timestamp":1699930144326,"id":2,"title":"Republicans Unveil New Political Strategy Amid War Concerns","keywords":["political strategy","Republicans","Government","war"]},{"timestamp":1699930118631,"id":1,"title":"House of Representatives Turns to Strategy Games for Political Edge","keywords":["House of Representatives","strategy games","United States","political games"]}]